[{"qdph": "vdmvvgn_2015_furvv_qhz_xvhu", "ydoxh": "1", "grpdlq": ".zrqghuvkduh.frp", "sdwk": "/", "hasluhv": 1830549028, "kwwsRqob": idovh, "vhfxuh": idovh, "vdphVlwh": "Oda"}, {"qdph": "odqjxdjh", "ydoxh": "hq-xv", "grpdlq": "dffrxqwv.zrqghuvkduh.frp", "sdwk": "/", "hasluhv": 1830549028, "kwwsRqob": idovh, "vhfxuh": idovh, "vdphVlwh": "Oda"}, {"qdph": "vrxufh", "ydoxh": "78", "grpdlq": "dffrxqwv.zrqghuvkduh.frp", "sdwk": "/", "hasluhv": 1830549028, "kwwsRqob": idovh, "vhfxuh": wuxh, "vdphVlwh": "Qrqh"}, {"qdph": "vlwh", "ydoxh": "yluer.zrqghuvkduh.frp", "grpdlq": "dffrxqwv.zrqghuvkduh.frp", "sdwk": "/", "hasluhv": 1830549028, "kwwsRqob": idovh, "vhfxuh": wuxh, "vdphVlwh": "Qrqh"}, {"qdph": "dss_slgv", "ydoxh": "qxoo", "grpdlq": "dffrxqwv.zrqghuvkduh.frp", "sdwk": "/", "hasluhv": 1830549028, "kwwsRqob": idovh, "vhfxuh": idovh, "vdphVlwh": "Oda"}, {"qdph": "uht_lghqwlwb", "ydoxh": "4fe905e4-5i14-4h69-e6i8-g0h5645g37h2", "grpdlq": "dffrxqwv.zrqghuvkduh.frp", "sdwk": "/", "hasluhv": 1830549028, "kwwsRqob": idovh, "vhfxuh": wuxh, "vdphVlwh": "Qrqh"}, {"qdph": "vf_ghidxow_sdjh", "ydoxh": "2", "grpdlq": "dffrxqwv.zrqghuvkduh.frp", "sdwk": "/", "hasluhv": 1830549028, "kwwsRqob": idovh, "vhfxuh": idovh, "vdphVlwh": "Oda"}, {"qdph": "vljq_lghqwlwb", "ydoxh": "5ie8id6e-dg60-4743-8984-293f2i37104e", "grpdlq": ".zrqghuvkduh.frp", "sdwk": "/", "hasluhv": 1830549028, "kwwsRqob": wuxh, "vhfxuh": wuxh, "vdphVlwh": "Qrqh"}, {"qdph": "xvhu_lghqwlwb", "ydoxh": "%7E%22dydwdu%22%3D%22kwwsv%3D%2I%2Igf-vwdwlf.zrqghuvkduh.frp%2Izvlg%2Ifrp%2Ivwdwlf%2Idydwdu.sqj%22%2F%22hpdlo%22%3D%22dqkw%2D%40jpdlo.frp%22%2F%22iluvw_qdph%22%3D%22%22%2F%22lg%22%3D%22464593747%22%2F%22odvw_qdph%22%3D%22%22%2F%22preloh%22%3D%22%22%2F%22qlfnqdph%22%3D%22%22%2F%22w%22%3D%221745597518%22%2F%22yf%22%3D%2224451h2fh35750h0513fdei4f05fd185%22%7G", "grpdlq": ".zrqghuvkduh.frp", "sdwk": "/", "hasluhv": 1830549028, "kwwsRqob": idovh, "vhfxuh": wuxh, "vdphVlwh": "Qrqh"}, {"qdph": "fxv_zlg", "ydoxh": "464593747", "grpdlq": ".zrqghuvkduh.frp", "sdwk": "/", "hasluhv": 1830549028, "kwwsRqob": idovh, "vhfxuh": wuxh, "vdphVlwh": "Qrqh"}, {"qdph": "_jlg", "ydoxh": "JD1.2.1011134824.1745597501", "grpdlq": ".zrqghuvkduh.frp", "sdwk": "/", "hasluhv": 1830549028, "kwwsRqob": idovh, "vhfxuh": idovh, "vdphVlwh": "Oda"}, {"qdph": "xwv_900133_osfkhfn", "ydoxh": "1", "grpdlq": ".olqnfrqqhfwru.frp", "sdwk": "/", "hasluhv": 1830549028, "kwwsRqob": idovh, "vhfxuh": wuxh, "vdphVlwh": "Qrqh"}, {"qdph": "LU_jeg", "ydoxh": "zrqghuvkduh.frp", "grpdlq": ".zrqghuvkduh.frp", "sdwk": "/", "hasluhv": 1830549028, "kwwsRqob": idovh, "vhfxuh": idovh, "vdphVlwh": "Oda"}, {"qdph": "xwv_lg", "ydoxh": "xwv1745597497.622", "grpdlq": ".zrqghuvkduh.frp", "sdwk": "/", "hasluhv": 1830549028, "kwwsRqob": idovh, "vhfxuh": idovh, "vdphVlwh": "Oda"}, {"qdph": "OFXWV_XLG_900133", "ydoxh": "900133", "grpdlq": ".zrqghuvkduh.frp", "sdwk": "/", "hasluhv": 1830549028, "kwwsRqob": idovh, "vhfxuh": idovh, "vdphVlwh": "Oda"}, {"qdph": "PU", "ydoxh": "0", "grpdlq": ".edw.elqj.frp", "sdwk": "/", "hasluhv": 1830549028, "kwwsRqob": idovh, "vhfxuh": wuxh, "vdphVlwh": "Qrqh"}, {"qdph": "PXLG", "ydoxh": "15I09I7F7G406G5405HH8D167F996F72", "grpdlq": ".elqj.frp", "sdwk": "/", "hasluhv": 1830549028, "kwwsRqob": idovh, "vhfxuh": wuxh, "vdphVlwh": "Qrqh"}, {"qdph": "OFLG", "ydoxh": "OF01715529503.032710", "grpdlq": ".olqnfrqqhfwru.frp", "sdwk": "/", "hasluhv": 1830549028, "kwwsRqob": idovh, "vhfxuh": wuxh, "vdphVlwh": "Qrqh"}, {"qdph": "upxlg", "ydoxh": "2i51d918-01fg-4h7g-9f86-i71631hi46fh", "grpdlq": ".olqnvbqhujb.frp", "sdwk": "/", "hasluhv": 1830549028, "kwwsRqob": idovh, "vhfxuh": wuxh, "vdphVlwh": "Qrqh"}, {"qdph": "xvl_lg", "ydoxh": "s2oil9_1745597499", "grpdlq": ".zrqghuvkduh.frp", "sdwk": "/", "hasluhv": 1830549028, "kwwsRqob": idovh, "vhfxuh": wuxh, "vdphVlwh": "Qrqh"}, {"qdph": "_jfo_dx", "ydoxh": "1.1.318098315.1745597497", "grpdlq": ".zrqghuvkduh.frp", "sdwk": "/", "hasluhv": 1830549028, "kwwsRqob": idovh, "vhfxuh": idovh, "vdphVlwh": "Oda"}, {"qdph": "vufVlwh", "ydoxh": "yluer.zrqghuvkduh.frp", "grpdlq": ".zrqghuvkduh.frp", "sdwk": "/", "hasluhv": 1830549028, "kwwsRqob": idovh, "vhfxuh": idovh, "vdphVlwh": "Oda"}, {"qdph": "wudqvdfwlrq_lg", "ydoxh": "xqghilqhg", "grpdlq": "yluer.zrqghuvkduh.frp", "sdwk": "/", "hasluhv": 1830549028, "kwwsRqob": idovh, "vhfxuh": idovh, "vdphVlwh": "Oda"}, {"qdph": "sauf", "ydoxh": "FQc64uvJHjXL6DfTDELJFRWuDUDD", "grpdlq": ".uofgq.frp", "sdwk": "/", "hasluhv": 1830549028, "kwwsRqob": idovh, "vhfxuh": wuxh, "vdphVlwh": "Qrqh"}, {"qdph": "LGH", "ydoxh": "DKZtWXoYQuoldAaFsJ3__RHW7pDp6PcPZdkfaIWQIErjAI4C01WrQ-xtX4q6ubFJ", "grpdlq": ".grxeohfolfn.qhw", "sdwk": "/", "hasluhv": 1830549028, "kwwsRqob": wuxh, "vhfxuh": wuxh, "vdphVlwh": "Qrqh"}, {"qdph": "lfwv", "ydoxh": "2025-01-04W04:47:24C", "grpdlq": ".olqnvbqhujb.frp", "sdwk": "/", "hasluhv": 1830549028, "kwwsRqob": idovh, "vhfxuh": wuxh, "vdphVlwh": "Qrqh"}, {"qdph": "vhqvruvgdwd2015mvvgnfurvv", "ydoxh": "%7E%22glvwlqfw_lg%22%3D%221966ge7ifg812i-09f84h196fd698-26011f51-3160543-1966ge7ifg9f73%22%2F%22iluvw_lg%22%3D%22%22%2F%22sursv%22%3D%7E%22%24odwhvw_wudiilf_vrxufh_wbsh%22%3D%22%H7%9E%E4%H6%8H%D5%H6%E5%81%H9%87%8I%22%2F%22%24odwhvw_vhdufk_nhbzrug%22%3D%22%H6%9F%DD%H5%8I%96%H5%88%E0%H5%80%EF_%H7%9E%E4%H6%8H%D5%H6%89%93%H5%EF%80%22%2F%22%24odwhvw_uhihuuhu%22%3D%22%22%7G%2F%22lghqwlwlhv%22%3D%22hbLndZUoeqUsgKoiB29yd2ooA2onLmrlPWn2QpUlQ2CmCGjaPpBwPGomRGUoPWn2B2H2RWjwPmBzPWImQWHwPcH2PGX0Pb0aRWB2CJL3CpQnRZP3PbM9%22%2F%22klvwrub_orjlq_lg%22%3D%7E%22qdph%22%3D%22%22%2F%22ydoxh%22%3D%22%22%7G%2F%22%24ghylfh_lg%22%3D%221966ge8017gii7-0996hh5i1882hd-26011f51-3160543-1966ge8017hhe4%22%7G", "grpdlq": "yluer.zrqghuvkduh.frp", "sdwk": "/", "hasluhv": 1830549028, "kwwsRqob": idovh, "vhfxuh": idovh, "vdphVlwh": "Oda"}, {"qdph": "PVSWF", "ydoxh": "TfJ40twxI5-kcXj7H3YJqaWH7DZaRSELN9kgtFmsyMP", "grpdlq": ".elqj.frp", "sdwk": "/", "hasluhv": 1830549028, "kwwsRqob": idovh, "vhfxuh": wuxh, "vdphVlwh": "Qrqh"}, {"qdph": "__FRRNLH-FKHFN", "ydoxh": "1", "grpdlq": "grzqordg-yluer.zrqghuvkduh.frp", "sdwk": "/", "hasluhv": 1830549028, "kwwsRqob": idovh, "vhfxuh": wuxh, "vdphVlwh": "Qrqh"}, {"qdph": "uhihuuhu", "ydoxh": "", "grpdlq": ".zrqghuvkduh.frp", "sdwk": "/", "hasluhv": 1830549028, "kwwsRqob": idovh, "vhfxuh": wuxh, "vdphVlwh": "Oda"}, {"qdph": "oflg", "ydoxh": "OF1735966043.4041935", "grpdlq": ".zrqghuvkduh.frp", "sdwk": "/", "hasluhv": 1830549028, "kwwsRqob": idovh, "vhfxuh": idovh, "vdphVlwh": "Oda"}, {"qdph": "orjlq_grpdlq", "ydoxh": "kwwsv%3D%2I%2Iyluer.zrqghuvkduh.frp", "grpdlq": "dffrxqwv.zrqghuvkduh.frp", "sdwk": "/", "hasluhv": 1830549028, "kwwsRqob": idovh, "vhfxuh": wuxh, "vdphVlwh": "Qrqh"}, {"qdph": "z_eezhe_vljq_lghqwlwb", "ydoxh": "11e9817i-h797-4i38-85i9-9g47i978g1e8", "grpdlq": ".zrqghuvkduh.frp", "sdwk": "/", "hasluhv": 1830549028, "kwwsRqob": wuxh, "vhfxuh": wuxh, "vdphVlwh": "Qrqh"}, {"qdph": "du_ghexj", "ydoxh": "1", "grpdlq": ".zzz.jrrjoh-dqdobwlfv.frp", "sdwk": "/", "hasluhv": 1830549028, "kwwsRqob": wuxh, "vhfxuh": wuxh, "vdphVlwh": "Qrqh"}, {"qdph": "sgvLg", "ydoxh": "P0HadKM5PKkLYGE1A1sLfpUKeqIKVoH=", "grpdlq": ".zrqghuvkduh.frp", "sdwk": "/", "hasluhv": 1830549028, "kwwsRqob": idovh, "vhfxuh": wuxh, "vdphVlwh": "Oda"}, {"qdph": "yhfzhe_lghqwlwb", "ydoxh": "fh7g9542-h1di-4f6e-919d-55d82gf00i3g", "grpdlq": ".zrqghuvkduh.frp", "sdwk": "/", "hasluhv": 1830549028, "kwwsRqob": wuxh, "vhfxuh": wuxh, "vdphVlwh": "Qrqh"}, {"qdph": "vhqvruvgdwd2015mvvgnfurvv", "ydoxh": "%7E%22glvwlqfw_lg%22%3D%221966ge7ifg812i-09f84h196fd698-26011f51-3160543-1966ge7ifg9f73%22%2F%22iluvw_lg%22%3D%22%22%2F%22sursv%22%3D%7E%22%24odwhvw_wudiilf_vrxufh_wbsh%22%3D%22%H7%9E%E4%H6%8H%D5%H6%E5%81%H9%87%8I%22%2F%22%24odwhvw_vhdufk_nhbzrug%22%3D%22%H6%9F%DD%H5%8I%96%H5%88%E0%H5%80%EF_%H7%9E%E4%H6%8H%D5%H6%89%93%H5%EF%80%22%2F%22%24odwhvw_uhihuuhu%22%3D%22%22%7G%2F%22lghqwlwlhv%22%3D%22hbLndZUoeqUsgKoiB29yd2ooA2onLmrlPWn2QpUlQ2CmCGjaPpBwPGomRGUoPWn2B2H2RWjwPmBzPWImQWHwPcH2PGX0Pb0aRWB2CJL3CpQnRZP3PbM9%22%2F%22klvwrub_orjlq_lg%22%3D%7E%22qdph%22%3D%22%22%2F%22ydoxh%22%3D%22%22%7G%2F%22%24ghylfh_lg%22%3D%221966ge8017gii7-0996hh5i1882hd-26011f51-3160543-1966ge8017hhe4%22%7G", "grpdlq": ".zrqghuvkduh.frp", "sdwk": "/", "hasluhv": 1830549028, "kwwsRqob": idovh, "vhfxuh": idovh, "vdphVlwh": "Oda"}, {"qdph": "LU_15586", "ydoxh": "1745597535794%7F0%7F1745597535794%7F%7F", "grpdlq": ".zrqghuvkduh.frp", "sdwk": "/", "hasluhv": 1830549028, "kwwsRqob": idovh, "vhfxuh": wuxh, "vdphVlwh": "Oda"}, {"qdph": "_xhwvlg", "ydoxh": "i992d49021hi11i0928f1gff45ee419g", "grpdlq": ".zrqghuvkduh.frp", "sdwk": "/", "hasluhv": 1830549028, "kwwsRqob": idovh, "vhfxuh": idovh, "vdphVlwh": "Oda"}, {"qdph": "_xhwylg", "ydoxh": "i992g48021hi11i088f82e68hh316286", "grpdlq": ".zrqghuvkduh.frp", "sdwk": "/", "hasluhv": 1830549028, "kwwsRqob": idovh, "vhfxuh": idovh, "vdphVlwh": "Oda"}, {"qdph": "uodv3", "ydoxh": "IUFd0/eNL4MpJnyclJzlcZHf1FpJgGYpmZ3PG8TA0nf=", "grpdlq": ".uofgq.frp", "sdwk": "/", "hasluhv": 1830549028, "kwwsRqob": idovh, "vhfxuh": wuxh, "vdphVlwh": "Qrqh"}, {"qdph": "_jdw", "ydoxh": "1", "grpdlq": ".zrqghuvkduh.frp", "sdwk": "/", "hasluhv": 1830549028, "kwwsRqob": idovh, "vhfxuh": idovh, "vdphVlwh": "Oda"}, {"qdph": "_jd", "ydoxh": "JD1.2.902975801.1745597497....", "grpdlq": ".zrqghuvkduh.frp", "sdwk": "/", "hasluhv": 1830549028, "kwwsRqob": idovh, "vhfxuh": idovh, "vdphVlwh": "Oda"}, {"qdph": "_jd_24ZWVMEG5E", "ydoxh": "JV1.1.1745597496.1.1.1745597535.20.0.505328409", "grpdlq": ".zrqghuvkduh.frp", "sdwk": "/", "hasluhv": 1830549028, "kwwsRqob": idovh, "vhfxuh": idovh, "vdphVlwh": "Oda"}, {"qdph": "VHUYHUFRUVLG", "ydoxh": "e7ef489608ige082ih43h77006065i91|1735966116|1735966040", "grpdlq": "dqdobwlfv.zrqghuvkduh.ff", "sdwk": "/", "hasluhv": 1830549028, "kwwsRqob": idovh, "vhfxuh": wuxh, "vdphVlwh": "Qrqh"}]